podlet/__init__.py
podlet/bootstrap.py
podlet/helpers.py
podlet/registrant.py
podlet/registrar.py
podlet/registry.py
podlet/resource.py
podlet/types.py
podlet-1.0.3.dist-info/METADATA
podlet-1.0.3.dist-info/WHEEL
podlet-1.0.3.dist-info/licenses/LICENSE
podlet-1.0.3.dist-info/RECORD
