Metadata-Version: 2.4
Name: podlet
Version: 1.0.3
Summary: Add your description here
Author: veloper
License-File: LICENSE
Requires-Python: >=3.11
Requires-Dist: pytest>=8.4.2
